<?xml version="1.0" encoding="utf-8" ?><DRUID><Rotation><RotationName>Resto_DarhangeR</RotationName><RotationDefault>false</RotationDefault><RotationList>-- Functions --|-- Druid Stuff --|-- Hotkeys --|-- Start Fight --|-- Autotarget script --|-- Stats Buffs / Flask --|-- All:Mouseover --|R:Tree of Life|R:Gift of the Wild|B:Thorns|-- All:Auto Buff (Raid/Party) --|-- Offensive Spells (H) --|-- Heal Engine --|-- All:Racial --|-- All:Healthstone --|-- All:Potions --|Use:Trinket (Heal)|B:Barkskin|R:Tranquility|R:Wild Growth|R:Swiftmend|R:Nourish|R:Abolish Poison|R:Remove Curse|R:Healing Touch|R:Regrowth|R:Regrowth (All)|R:Rejuvenation (All)</RotationList><RequireCombat>false</RequireCombat><RotationNotes>Notes:
- DO NOT TARGET A FRIENDLY PLAYER;</RotationNotes></Rotation><Rotation><RotationName>FeralBear_Tank_DarhangeR</RotationName><RotationDefault>false</RotationDefault><RotationList>-- Feral Function --|-- Druid Stuff --|F:-- Hotkeys --|-- Start Fight --|-- Autotarget script --|-- Stats Buffs / Flask --|-- All:Mouseover --|R:Gift of the Wild|-- All:Auto Buff (Raid/Party) --|B:Thorns|F:Bear Form|-- Offensive Spells --|-- All:Racial --|-- All:Healthstone --|-- All:Potions --|B:Barkskin|F:Frenzied Regeneration|F:Survival Instincts|F:Berserk (Bear)|F:Swipe (Bear)|F:Bash|F:Faerie Fire|F:Enrage|F:Mangle (Bear)|F:Lacerate|F:Maul</RotationList><RequireCombat>false</RequireCombat><RotationNotes>Specific commands:

- Press Right Alt for use Auto Swipe;
- Hold Left Alt for use Bash;</RotationNotes></Rotation><Rotation><RotationName>Balance_DPS_DarhangeR</RotationName><RotationDefault>false</RotationDefault><RotationList>-- Functions --|-- Druid Stuff --|B:-- Hotkeys --|-- Start Fight --|-- Autotarget script --|-- Stats Buffs / Flask --|-- All:Mouseover --|R:Gift of the Wild|B:Thorns|B:Moonkin Form|-- All:Auto Buff (Raid/Party) --|-- Offensive Spells --|-- All:Racial --|-- All:Healthstone --|-- All:Potions --|B:Barkskin|B:Nature&amp;apos;s Grasp|B:Typhoon|B:Hurricane|B:Force of Nature|B:Faerie Fire|B:Insect Swarm|B:Moonfire|B:Eclipse|B:Wrath|B:Starfire</RotationList><RequireCombat>false</RequireCombat><RotationNotes>Specific commands:

- Hold Left Shift for use Force of Nature;
- Hold Left Alt for use Typhoon;
- Hold Right Alt for use Hurricane;</RotationNotes></Rotation><Rotation><RotationName>FeralCat_DPS_DarhangeR</RotationName><RotationDefault>false</RotationDefault><RotationList>-- Feral Function --|-- Druid Stuff --|F:-- Hotkeys --|-- Start Fight --|-- Autotarget script --|-- All:Mouseover --|R:Gift of the Wild|-- All:Auto Buff (Raid/Party) --|B:Thorns|F:Cat Form|-- Offensive Spells --|-- All:Racial --|-- All:Healthstone --|-- All:Potions --|F:Swipe (Cat)|F:Rejuvenation (Cat)|B:Barkskin|F:Survival Instincts|F:Faerie Fire|F:Tiger&amp;apos;s Fury|F:Berserk|F:Ferocious Bite|F:Savage Roar|F:Rip|F:Savage Roar()|F:Mangle (Cat)|F:Rake|F:Shred</RotationList><RequireCombat>false</RequireCombat><RotationNotes>Specific commands:

- Hold Left Alt for use Rejuvenation;
- Press Right Alt for use Auto Swipe;</RotationNotes></Rotation><Rotation><RotationName>Resto25_DarhangeR</RotationName><RotationDefault>false</RotationDefault><RotationList>-- Functions --|-- Druid Stuff --|-- Hotkeys --|-- Start Fight --|-- Autotarget script --|-- Stats Buffs / Flask --|-- All:Mouseover --|R:Tree of Life|R:Gift of the Wild|B:Thorns|-- All:Auto Buff (Raid/Party) --|-- Offensive Spells (H) --|-- Heal Engine --|-- All:Racial --|-- All:Healthstone --|-- All:Potions --|Use:Trinket (Heal)|B:Barkskin|R:Tranquility|R:Wild Growth|R:Rejuvenation|R:Swiftmend|R:Abolish Poison|R:Remove Curse|R:Healing Touch|R:Regrowth|R:Regrowth (All)|R:Rejuvenation (All)|R:Nourish|R:Lifebloom</RotationList><RequireCombat>false</RequireCombat><RotationNotes>Notes:
- DO NOT TARGET A FRIENDLY PLAYER;</RotationNotes></Rotation></DRUID>