<?xml version="1.0" encoding="utf-8" ?><PRIEST><Rotation><RotationName>Heal_Holy25_DarhangeR</RotationName><RotationDefault>false</RotationDefault><RotationList>-- Function --|-- Hotkeys --|-- Start Fight --|-- Stats Buffs / Flask --|-- Interrupt Engine --|D:Mass Dispel|D:Inner Fire|D:Prayer of Fortitude|D:Prayer of Spirit|S:Prayer of Shadow Protection|S:Vampiric Embrace|-- Offensive Spells --|Use:Mouseover Skill|H:Heal Target Eng(Simp)|S:Fade|H:Guardian Spirit|H:Desperate Prayer|H:Power Word: Shield|H:Prayer of Mending|H:Circle of Healing|H:Prayer of Healing|H:Renew|H:Greater Heal|H:Binding Heal|H:Flash Heal|D:Dispel Magic|D:Cure Disease|H:Renew (Alle)</RotationList><RequireCombat>false</RequireCombat><RotationNotes>Specific commands:
- Hold Left Alt for use Mass Dispel;
- Focus Target for use Power Word:Shield;

Notes:
- DO NOT TARGET A FRIENDLY PLAYER;</RotationNotes></Rotation><Rotation><RotationName>Shadow_DPS_DarhangeR</RotationName><RotationDefault>false</RotationDefault><RotationList>-- Function --|S:-- Hotkeys --|-- Start Fight --|-- Stats Buffs / Flask --|-- Interrupt Engine --|-- Autotarget --|Use:Mouseover Skill|D:Inner Fire|D:Prayer of Fortitude|D:Prayer of Spirit|S:Prayer of Shadow Protection|S:Vampiric Embrace|S:Shadowform|-- Offensive Spells --|D:Heal Target Eng(Simp)|D:Mass Dispel|S:Fade|S:Dispersion|All:Racial|S:Shadowfiend|S:Shadow Word: Death(Always)|S:Vampiric Touch|S:Shadow Word: Pain|S:Mind Sear (AoE)|S:Devouring Plague|S:Mind Blast|S:Mind Flay|D:Dispel Magic|D:Cure Disease</RotationList><RequireCombat>false</RequireCombat><RotationNotes>Specific commands:
- Hold Left Alt for use Mass Dispel;
- Left Shift for enabled/disabled Mind Sear (AoE);</RotationNotes></Rotation></PRIEST>